[
    {
      "image": "/public/figuras/Interagindo/OI.png",
      "text": "oi",
      "name": "oi",
      "category": "Interagindo"
    },
    {
      "image": "/public/figuras/Interagindo/POR NADA.png",
      "text": "por favor",
      "name": "por favor",
      "category": "Interagindo"
    },
    {
      "image": "/public/figuras/Interagindo/POR NADA.png",
      "text": "por nada",
      "name": "por nada",
      "category": "Interagindo"
    },
    {
      "image": "/public/figuras/Interagindo/TCHAU.png",
      "text": "tchau",
      "name": "tchau",
      "category": "Interagindo"
    },
    {
      "image": "/public/figuras/Interagindo/OBRIGADO.png",
      "text": "obrigado",
      "name": "obrigado",
      "category": "Interagindo"
    },
    {
      "image": "/public/figuras/Interagindo/DESCULPA.png",
      "text": "Desculpa",
      "name": "Desculpa",
      "category": "Interagindo"
    },
    {
      "image": "/public/figuras/Interagindo/COM LICENÇA.png",
      "text": "com licença",
      "name": "com licença",
      "category": "Interagindo"
    },
    {
      "image": "/public/figuras/Interagindo/BOM DIA.png",
      "text": "bom dia",
      "name": "bom dia",
      "category": "Interagindo"
    },
    {
      "image": "/public/figuras/Interagindo/BOA TARDE.png",
      "text": "boa tarde",
      "name": "boa tarde",
      "category": "Interagindo"
    },
    {
      "image": "/public/figuras/Interagindo/BOA NOITE.png",
      "text": "boa noite",
      "name": "boa noite",
      "category": "Interagindo"
    }
  ]