[
  {
    "image": "/figuras/Alfabeto/A.png",
    "text": "A",
    "name": "A",
    "category": "Alfabeto"
  },
  {
    "image": "/figuras/Alfabeto/B.png",
    "text": "B",
    "name": "B",
    "category": "Alfabeto"
  },
  {
    "image": "/figuras/Alfabeto/C.png",
    "text": "C",
    "name": "C",
    "category": "Alfabeto"
  },
  {
    "image": "/figuras/Alfabeto/D.png",
    "text": "D",
    "name": "D",
    "category": "Alfabeto"
  },
  {
    "image": "/figuras/Alfabeto/E.png",
    "text": "E",
    "name": "E",
    "category": "Alfabeto"
  },
  {
    "image": "/figuras/Alfabeto/F.png",
    "text": "F",
    "name": "F",
    "category": "Alfabeto"
  },
  {
    "image": "/figuras/Alfabeto/G.png",
    "text": "G",
    "name": "G",
    "category": "Alfabeto"
  },
  {
    "image": "/figuras/Alfabeto/H.png",
    "text": "H",
    "name": "H",
    "category": "Alfabeto"
  },
  {
    "image": "/figuras/Alfabeto/I.png",
    "text": "I",
    "name": "I",
    "category": "Alfabeto"
  },
  {
    "image": "/figuras/Alfabeto/J.png",
    "text": "J",
    "name": "J",
    "category": "Alfabeto"
  },
  {
    "image": "/figuras/Alfabeto/K.png",
    "text": "K",
    "name": "K",
    "category": "Alfabeto"
  },
  {
    "image": "/figuras/Alfabeto/L.png",
    "text": "L",
    "name": "L",
    "category": "Alfabeto"
  },
  {
    "image": "/figuras/Alfabeto/M.png",
    "text": "M",
    "name": "M",
    "category": "Alfabeto"
  },
  {
    "image": "/figuras/Alfabeto/N.png",
    "text": "N",
    "name": "N",
    "category": "Alfabeto"
  },
  {
    "image": "/figuras/Alfabeto/O.png",
    "text": "O",
    "name": "O",
    "category": "Alfabeto"
  },
  {
    "image": "/figuras/Alfabeto/P.png",
    "text": "P",
    "name": "P",
    "category": "Alfabeto"
  },
  {
    "image": "/figuras/Alfabeto/Q.png",
    "text": "Q",
    "name": "Q",
    "category": "Alfabeto"
  },
  {
    "image": "/figuras/Alfabeto/R.png",
    "text": "R",
    "name": "R",
    "category": "Alfabeto"
  },
  {
    "image": "/figuras/Alfabeto/S.png",
    "text": "S",
    "name": "S",
    "category": "Alfabeto"
  },
  {
    "image": "/figuras/Alfabeto/T.png",
    "text": "T",
    "name": "T",
    "category": "Alfabeto"
  },
  {
    "image": "/figuras/Alfabeto/U.png",
    "text": "U",
    "name": "U",
    "category": "Alfabeto"
  },
  {
    "image": "/figuras/Alfabeto/V.png",
    "text": "V",
    "name": "V",
    "category": "Alfabeto"
  },
  {
    "image": "/figuras/Alfabeto/W.png",
    "text": "W",
    "name": "W",
    "category": "Alfabeto"
  },
  {
    "image": "/figuras/Alfabeto/X.png",
    "text": "X",
    "name": "X",
    "category": "Alfabeto"
  },
  {
    "image": "/figuras/Alfabeto/Y.png",
    "text": "Y",
    "name": "Y",
    "category": "Alfabeto"
  },
  {
    "image": "/figuras/Alfabeto/Z.png",
    "text": "Z",
    "name": "Z",
    "category": "Alfabeto"
  },
  {
    "image": "/figuras/Animais/ABELHA.png",
    "text": "ABELHA",
    "name": "ABELHA",
    "category": "Animais"
  },
  {
    "image": "/figuras/Animais/BALEIA.png",
    "text": "BALEIA",
    "name": "BALEIA",
    "category": "Animais"
  },
  {
    "image": "/figuras/Animais/BEIJA-FLOR.png",
    "text": "BEIJA-FLOR",
    "name": "BEIJA-FLOR",
    "category": "Animais"
  },
  {
    "image": "/figuras/Animais/BESOURO.png",
    "text": "BESOURO",
    "name": "BESOURO",
    "category": "Animais"
  },
  {
    "image": "/figuras/Animais/BOI.png",
    "text": "BOI",
    "name": "BOI",
    "category": "Animais"
  },
  {
    "image": "/figuras/Animais/BORBOLETA.png",
    "text": "BORBOLETA",
    "name": "BORBOLETA",
    "category": "Animais"
  },
  {
    "image": "/figuras/Animais/CABRA.png",
    "text": "CABRA",
    "name": "CABRA",
    "category": "Animais"
  },
  {
    "image": "/figuras/Animais/CACHORRO.png",
    "text": "CACHORRO",
    "name": "CACHORRO",
    "category": "Animais"
  },
  {
    "image": "/figuras/Animais/CARANGUEJO.png",
    "text": "CARANGUEJO",
    "name": "CARANGUEJO",
    "category": "Animais"
  },
  {
    "image": "/figuras/Animais/CAVALO.png",
    "text": "CAVALO",
    "name": "CAVALO",
    "category": "Animais"
  },
  {
    "image": "/figuras/Animais/COBRA.png",
    "text": "COBRA",
    "name": "COBRA",
    "category": "Animais"
  },
  {
    "image": "/figuras/Animais/COELHO.png",
    "text": "COELHO",
    "name": "COELHO",
    "category": "Animais"
  },
  {
    "image": "/figuras/Animais/CORUJA.png",
    "text": "CORUJA",
    "name": "CORUJA",
    "category": "Animais"
  },
  {
    "image": "/figuras/Animais/ELEFANTE.png",
    "text": "ELEFANTE",
    "name": "ELEFANTE",
    "category": "Animais"
  },
  {
    "image": "/figuras/Animais/FOCA.png",
    "text": "FOCA",
    "name": "FOCA",
    "category": "Animais"
  },
  {
    "image": "/figuras/Animais/GALINHA.png",
    "text": "GALINHA",
    "name": "GALINHA",
    "category": "Animais"
  },
  {
    "image": "/figuras/Animais/GALO.png",
    "text": "GALO",
    "name": "GALO",
    "category": "Animais"
  },
  {
    "image": "/figuras/Animais/GATO.png",
    "text": "GATO",
    "name": "GATO",
    "category": "Animais"
  },
  {
    "image": "/figuras/Animais/GIRAFA.png",
    "text": "GIRAFA",
    "name": "GIRAFA",
    "category": "Animais"
  },
  {
    "image": "/figuras/Animais/GORILA.png",
    "text": "GORILA",
    "name": "GORILA",
    "category": "Animais"
  },
  {
    "image": "/figuras/Animais/GRILO.png",
    "text": "GRILO",
    "name": "GRILO",
    "category": "Animais"
  },
  {
    "image": "/figuras/Animais/HIPOPÓTAMO.png",
    "text": "HIPOPÓTAMO",
    "name": "HIPOPÓTAMO",
    "category": "Animais"
  },
  {
    "image": "/figuras/Animais/JACARÉ.png",
    "text": "JACARÉ",
    "name": "JACARÉ",
    "category": "Animais"
  },
  {
    "image": "/figuras/Animais/JOANINHA.png",
    "text": "JOANINHA",
    "name": "JOANINHA",
    "category": "Animais"
  },
  {
    "image": "/figuras/Animais/LAGARTA.png",
    "text": "LAGARTA",
    "name": "LAGARTA",
    "category": "Animais"
  },
  {
    "image": "/figuras/Animais/LEÃO.png",
    "text": "LEÃO",
    "name": "LEÃO",
    "category": "Animais"
  },
  {
    "image": "/figuras/Animais/MACACO.png",
    "text": "MACACO",
    "name": "MACACO",
    "category": "Animais"
  },
  {
    "image": "/figuras/Animais/MORCEGO.png",
    "text": "MORCEGO",
    "name": "MORCEGO",
    "category": "Animais"
  },
  {
    "image": "/figuras/Animais/OVELHA.png",
    "text": "OVELHA",
    "name": "OVELHA",
    "category": "Animais"
  },
  {
    "image": "/figuras/Animais/PATO.png",
    "text": "PATO",
    "name": "PATO",
    "category": "Animais"
  },
  {
    "image": "/figuras/Animais/PAVÃO.png",
    "text": "PAVÃO",
    "name": "PAVÃO",
    "category": "Animais"
  },
  {
    "image": "/figuras/Animais/PEIXE.png",
    "text": "PEIXE",
    "name": "PEIXE",
    "category": "Animais"
  },
  {
    "image": "/figuras/Animais/PORCO.png",
    "text": "PORCO",
    "name": "PORCO",
    "category": "Animais"
  },
  {
    "image": "/figuras/Animais/PÁSSARO.png",
    "text": "PÁSSARO",
    "name": "PÁSSARO",
    "category": "Animais"
  },
  {
    "image": "/figuras/Animais/RATO.png",
    "text": "RATO",
    "name": "RATO",
    "category": "Animais"
  },
  {
    "image": "/figuras/Animais/RENA.png",
    "text": "RENA",
    "name": "RENA",
    "category": "Animais"
  },
  {
    "image": "/figuras/Animais/RINOCERONTE.png",
    "text": "RINOCERONTE",
    "name": "RINOCERONTE",
    "category": "Animais"
  },
  {
    "image": "/figuras/Animais/SAPO.png",
    "text": "SAPO",
    "name": "SAPO",
    "category": "Animais"
  },
  {
    "image": "/figuras/Animais/TARTARUGA.png",
    "text": "TARTARUGA",
    "name": "TARTARUGA",
    "category": "Animais"
  },
  {
    "image": "/figuras/Animais/TIGRE.png",
    "text": "TIGRE",
    "name": "TIGRE",
    "category": "Animais"
  },
  {
    "image": "/figuras/Animais/TUBARÃO.png",
    "text": "TUBARÃO",
    "name": "TUBARÃO",
    "category": "Animais"
  },
  {
    "image": "/figuras/Animais/URSO PANDA.png",
    "text": "URSO PANDA",
    "name": "URSO PANDA",
    "category": "Animais"
  },
  {
    "image": "/figuras/Animais/ZEBRA.png",
    "text": "ZEBRA",
    "name": "ZEBRA",
    "category": "Animais"
  },
  {
    "image": "/figuras/Alimentação/ABACATE.png",
    "text": "ABACATE",
    "name": "ABACATE",
    "category": "Alimentação"
  },
  {
    "image": "/figuras/Alimentação/ARROZ.png",
    "text": "ARROZ",
    "name": "ARROZ",
    "category": "Alimentação"
  },
  {
    "image": "/figuras/Alimentação/BALA.png",
    "text": "BALA",
    "name": "BALA",
    "category": "Alimentação"
  },
  {
    "image": "/figuras/Alimentação/BANANA.png",
    "text": "BANANA",
    "name": "BANANA",
    "category": "Alimentação"
  },
  {
    "image": "/figuras/Alimentação/BISCOITO.png",
    "text": "BISCOITO",
    "name": "BISCOITO",
    "category": "Alimentação"
  },
  {
    "image": "/figuras/Alimentação/BOLO.png",
    "text": "BOLO",
    "name": "BOLO",
    "category": "Alimentação"
  },
  {
    "image": "/figuras/Alimentação/CACHORRO-QUENTE.png",
    "text": "CACHORRO-QUENTE",
    "name": "CACHORRO-QUENTE",
    "category": "Alimentação"
  },
  {
    "image": "/figuras/Alimentação/CAFÉ-1.png",
    "text": "CAFÉ-1",
    "name": "CAFÉ-1",
    "category": "Alimentação"
  },
  {
    "image": "/figuras/Alimentação/CAFÉ.png",
    "text": "CAFÉ",
    "name": "CAFÉ",
    "category": "Alimentação"
  },
  {
    "image": "/figuras/Alimentação/CARNE.png",
    "text": "CARNE",
    "name": "CARNE",
    "category": "Alimentação"
  },
  {
    "image": "/figuras/Alimentação/CENOURA.png",
    "text": "CENOURA",
    "name": "CENOURA",
    "category": "Alimentação"
  },
  {
    "image": "/figuras/Alimentação/CEREJA.png",
    "text": "CEREJA",
    "name": "CEREJA",
    "category": "Alimentação"
  },
  {
    "image": "/figuras/Alimentação/CHÁ.png",
    "text": "CHÁ",
    "name": "CHÁ",
    "category": "Alimentação"
  },
  {
    "image": "/figuras/Alimentação/CUPCAKE.png",
    "text": "CUPCAKE",
    "name": "CUPCAKE",
    "category": "Alimentação"
  },
  {
    "image": "/figuras/Alimentação/FEIJÃO.png",
    "text": "FEIJÃO",
    "name": "FEIJÃO",
    "category": "Alimentação"
  },
  {
    "image": "/figuras/Alimentação/FRANGO.png",
    "text": "FRANGO",
    "name": "FRANGO",
    "category": "Alimentação"
  },
  {
    "image": "/figuras/Alimentação/FRUTAS.png",
    "text": "FRUTAS",
    "name": "FRUTAS",
    "category": "Alimentação"
  },
  {
    "image": "/figuras/Alimentação/IOGURTE.png",
    "text": "IOGURTE",
    "name": "IOGURTE",
    "category": "Alimentação"
  },
  {
    "image": "/figuras/Alimentação/LANCHE.png",
    "text": "LANCHE",
    "name": "LANCHE",
    "category": "Alimentação"
  },
  {
    "image": "/figuras/Alimentação/LARANJA.png",
    "text": "LARANJA",
    "name": "LARANJA",
    "category": "Alimentação"
  },
  {
    "image": "/figuras/Alimentação/LEITE.png",
    "text": "LEITE",
    "name": "LEITE",
    "category": "Alimentação"
  },
  {
    "image": "/figuras/Alimentação/MACARRÃO.png",
    "text": "MACARRÃO",
    "name": "MACARRÃO",
    "category": "Alimentação"
  },
  {
    "image": "/figuras/Alimentação/MAÇÃ.png",
    "text": "MAÇÃ",
    "name": "MAÇÃ",
    "category": "Alimentação"
  },
  {
    "image": "/figuras/Alimentação/MELANCIA.png",
    "text": "MELANCIA",
    "name": "MELANCIA",
    "category": "Alimentação"
  },
  {
    "image": "/figuras/Alimentação/MORANGO.png",
    "text": "MORANGO",
    "name": "MORANGO",
    "category": "Alimentação"
  },
  {
    "image": "/figuras/Alimentação/PICOLÉ.png",
    "text": "PICOLÉ",
    "name": "PICOLÉ",
    "category": "Alimentação"
  },
  {
    "image": "/figuras/Alimentação/PIPOCA.png",
    "text": "PIPOCA",
    "name": "PIPOCA",
    "category": "Alimentação"
  },
  {
    "image": "/figuras/Alimentação/PIRULITO.png",
    "text": "PIRULITO",
    "name": "PIRULITO",
    "category": "Alimentação"
  },
  {
    "image": "/figuras/Alimentação/PIZZA.png",
    "text": "PIZZA",
    "name": "PIZZA",
    "category": "Alimentação"
  },
  {
    "image": "/figuras/Alimentação/PÃO.png",
    "text": "PÃO",
    "name": "PÃO",
    "category": "Alimentação"
  },
  {
    "image": "/figuras/Alimentação/REFRIGERANTE.png",
    "text": "REFRIGERANTE",
    "name": "REFRIGERANTE",
    "category": "Alimentação"
  },
  {
    "image": "/figuras/Alimentação/ROSCA.png",
    "text": "ROSCA",
    "name": "ROSCA",
    "category": "Alimentação"
  },
  {
    "image": "/figuras/Alimentação/SALADA.png",
    "text": "SALADA",
    "name": "SALADA",
    "category": "Alimentação"
  },
  {
    "image": "/figuras/Alimentação/SOPA.png",
    "text": "SOPA",
    "name": "SOPA",
    "category": "Alimentação"
  },
  {
    "image": "/figuras/Alimentação/SORVETE.png",
    "text": "SORVETE",
    "name": "SORVETE",
    "category": "Alimentação"
  },
  {
    "image": "/figuras/Alimentação/SUCO.png",
    "text": "SUCO",
    "name": "SUCO",
    "category": "Alimentação"
  },
  {
    "image": "/figuras/Alimentação/TAPIOCA.png",
    "text": "TAPIOCA",
    "name": "TAPIOCA",
    "category": "Alimentação"
  },
  {
    "image": "/figuras/Alimentação/TORTA.png",
    "text": "TORTA",
    "name": "TORTA",
    "category": "Alimentação"
  },
  {
    "image": "/figuras/Alimentação/UVA.png",
    "text": "UVA",
    "name": "UVA",
    "category": "Alimentação"
  },
  {
    "image": "/figuras/Alimentação/ÁGUA.png",
    "text": "ÁGUA",
    "name": "ÁGUA",
    "category": "Alimentação"
  },
  {
    "image": "/figuras/Cores/AMARELO.png",
    "text": "AMARELO",
    "name": "AMARELO",
    "category": "Cores"
  },
  {
    "image": "/figuras/Cores/AZUL.png",
    "text": "AZUL",
    "name": "AZUL",
    "category": "Cores"
  },
  {
    "image": "/figuras/Cores/BRANCO.png",
    "text": "BRANCO",
    "name": "BRANCO",
    "category": "Cores"
  },
  {
    "image": "/figuras/Cores/LARANJA.png",
    "text": "LARANJA",
    "name": "LARANJA",
    "category": "Cores"
  },
  {
    "image": "/figuras/Cores/MARROM.png",
    "text": "MARROM",
    "name": "MARROM",
    "category": "Cores"
  },
  {
    "image": "/figuras/Cores/PRETO.png",
    "text": "PRETO",
    "name": "PRETO",
    "category": "Cores"
  },
  {
    "image": "/figuras/Cores/ROSA.png",
    "text": "ROSA",
    "name": "ROSA",
    "category": "Cores"
  },
  {
    "image": "/figuras/Cores/ROXO.png",
    "text": "ROXO",
    "name": "ROXO",
    "category": "Cores"
  },
  {
    "image": "/figuras/Cores/VERDE.png",
    "text": "VERDE",
    "name": "VERDE",
    "category": "Cores"
  },
  {
    "image": "/figuras/Cores/VERMELHO.png",
    "text": "VERMELHO",
    "name": "VERMELHO",
    "category": "Cores"
  },
  {
    "image": "/figuras/Diversão/BASQUETE.png",
    "text": "BASQUETE",
    "name": "BASQUETE",
    "category": "Diversão"
  },
  {
    "image": "/figuras/Diversão/BICICLETA.png",
    "text": "BICICLETA",
    "name": "BICICLETA",
    "category": "Diversão"
  },
  {
    "image": "/figuras/Diversão/BONECA.png",
    "text": "BONECA",
    "name": "BONECA",
    "category": "Diversão"
  },
  {
    "image": "/figuras/Diversão/CARRINHO.png",
    "text": "CARRINHO",
    "name": "CARRINHO",
    "category": "Diversão"
  },
  {
    "image": "/figuras/Diversão/CONVERSAR.png",
    "text": "CONVERSAR",
    "name": "CONVERSAR",
    "category": "Diversão"
  },
  {
    "image": "/figuras/Diversão/DADOS.png",
    "text": "DADOS",
    "name": "DADOS",
    "category": "Diversão"
  },
  {
    "image": "/figuras/Diversão/DESENHO.png",
    "text": "DESENHO",
    "name": "DESENHO",
    "category": "Diversão"
  },
  {
    "image": "/figuras/Diversão/DINOSSAURO.png",
    "text": "DINOSSAURO",
    "name": "DINOSSAURO",
    "category": "Diversão"
  },
  {
    "image": "/figuras/Diversão/FUTEBOL.png",
    "text": "FUTEBOL",
    "name": "FUTEBOL",
    "category": "Diversão"
  },
  {
    "image": "/figuras/Diversão/LABIRINTO.png",
    "text": "LABIRINTO",
    "name": "LABIRINTO",
    "category": "Diversão"
  },
  {
    "image": "/figuras/Diversão/LIVRO.png",
    "text": "LIVRO",
    "name": "LIVRO",
    "category": "Diversão"
  },
  {
    "image": "/figuras/Diversão/MÚSICA.png",
    "text": "MÚSICA",
    "name": "MÚSICA",
    "category": "Diversão"
  },
  {
    "image": "/figuras/Diversão/PING PONG.png",
    "text": "PING PONG",
    "name": "PING PONG",
    "category": "Diversão"
  },
  {
    "image": "/figuras/Diversão/PIPA.png",
    "text": "PIPA",
    "name": "PIPA",
    "category": "Diversão"
  },
  {
    "image": "/figuras/Diversão/PISCINA.png",
    "text": "PISCINA",
    "name": "PISCINA",
    "category": "Diversão"
  },
  {
    "image": "/figuras/Diversão/QUEBRA-CABEÇA.png",
    "text": "QUEBRA-CABEÇA",
    "name": "QUEBRA-CABEÇA",
    "category": "Diversão"
  },
  {
    "image": "/figuras/Diversão/ROBÔ.png",
    "text": "ROBÔ",
    "name": "ROBÔ",
    "category": "Diversão"
  },
  {
    "image": "/figuras/Diversão/TABLET.png",
    "text": "TABLET",
    "name": "TABLET",
    "category": "Diversão"
  },
  {
    "image": "/figuras/Diversão/TELEVISÃO.png",
    "text": "TELEVISÃO",
    "name": "TELEVISÃO",
    "category": "Diversão"
  },
  {
    "image": "/figuras/Diversão/VOLEI.png",
    "text": "VOLEI",
    "name": "VOLEI",
    "category": "Diversão"
  },
  {
    "image": "/figuras/Diversão/VÍDEO GAME.png",
    "text": "VÍDEO GAME",
    "name": "VÍDEO GAME",
    "category": "Diversão"
  },
  {
    "image": "/figuras/Escola/BANHEIRO.png",
    "text": "BANHEIRO",
    "name": "BANHEIRO",
    "category": "Escola"
  },
  {
    "image": "/figuras/Escola/BIBLIOTECA.png",
    "text": "BIBLIOTECA",
    "name": "BIBLIOTECA",
    "category": "Escola"
  },
  {
    "image": "/figuras/Escola/DIPLOMA.png",
    "text": "DIPLOMA",
    "name": "DIPLOMA",
    "category": "Escola"
  },
  {
    "image": "/figuras/Escola/ESCOLA.png",
    "text": "ESCOLA",
    "name": "ESCOLA",
    "category": "Escola"
  },
  {
    "image": "/figuras/Escola/GLOBO TERRESTRE.png",
    "text": "GLOBO TERRESTRE",
    "name": "GLOBO TERRESTRE",
    "category": "Escola"
  },
  {
    "image": "/figuras/Escola/INFORMÁTICA.png",
    "text": "INFORMÁTICA",
    "name": "INFORMÁTICA",
    "category": "Escola"
  },
  {
    "image": "/figuras/Escola/LIVROS.png",
    "text": "LIVROS",
    "name": "LIVROS",
    "category": "Escola"
  },
  {
    "image": "/figuras/Escola/MOCHILA.png",
    "text": "MOCHILA",
    "name": "MOCHILA",
    "category": "Escola"
  },
  {
    "image": "/figuras/Escola/PARQUE.png",
    "text": "PARQUE",
    "name": "PARQUE",
    "category": "Escola"
  },
  {
    "image": "/figuras/Escola/PROFESSOR.png",
    "text": "PROFESSOR",
    "name": "PROFESSOR",
    "category": "Escola"
  },
  {
    "image": "/figuras/Escola/PÁTIO.png",
    "text": "PÁTIO",
    "name": "PÁTIO",
    "category": "Escola"
  },
  {
    "image": "/figuras/Escola/QUADRA.png",
    "text": "QUADRA",
    "name": "QUADRA",
    "category": "Escola"
  },
  {
    "image": "/figuras/Escola/REFEITÓRIO.png",
    "text": "REFEITÓRIO",
    "name": "REFEITÓRIO",
    "category": "Escola"
  },
  {
    "image": "/figuras/Escola/SALA DE AULA.png",
    "text": "SALA DE AULA",
    "name": "SALA DE AULA",
    "category": "Escola"
  },
  {
    "image": "/figuras/Família/AVÓ.png",
    "text": "AVÓ",
    "name": "AVÓ",
    "category": "Família"
  },
  {
    "image": "/figuras/Família/AVÔ.png",
    "text": "AVÔ",
    "name": "AVÔ",
    "category": "Família"
  },
  {
    "image": "/figuras/Família/IRMÃ.png",
    "text": "IRMÃ",
    "name": "IRMÃ",
    "category": "Família"
  },
  {
    "image": "/figuras/Família/IRMÃO.png",
    "text": "IRMÃO",
    "name": "IRMÃO",
    "category": "Família"
  },
  {
    "image": "/figuras/Família/MÃE.png",
    "text": "MÃE",
    "name": "MÃE",
    "category": "Família"
  },
  {
    "image": "/figuras/Família/PAI.png",
    "text": "PAI",
    "name": "PAI",
    "category": "Família"
  },
  {
    "image": "/figuras/Família/PRIMA.png",
    "text": "PRIMA",
    "name": "PRIMA",
    "category": "Família"
  },
  {
    "image": "/figuras/Família/PRIMO.png",
    "text": "PRIMO",
    "name": "PRIMO",
    "category": "Família"
  },
  {
    "image": "/figuras/Família/TIA.png",
    "text": "TIA",
    "name": "TIA",
    "category": "Família"
  },
  {
    "image": "/figuras/Família/TIO.png",
    "text": "TIO",
    "name": "TIO",
    "category": "Família"
  },
  {
    "image": "/figuras/Formas/CÍRCULO.png",
    "text": "CÍRCULO",
    "name": "CÍRCULO",
    "category": "Formas"
  },
  {
    "image": "/figuras/Formas/QUADRADO.png",
    "text": "QUADRADO",
    "name": "QUADRADO",
    "category": "Formas"
  },
  {
    "image": "/figuras/Formas/RETÂNGULO.png",
    "text": "RETÂNGULO",
    "name": "RETÂNGULO",
    "category": "Formas"
  },
  {
    "image": "/figuras/Formas/TRIÂNGULO.png",
    "text": "TRIÂNGULO",
    "name": "TRIÂNGULO",
    "category": "Formas"
  },
  {
    "image": "/figuras/Interações/BOA NOITE.png",
    "text": "BOA NOITE",
    "name": "BOA NOITE",
    "category": "Interações"
  },
  {
    "image": "/figuras/Interações/BOA TARDE.png",
    "text": "BOA TARDE",
    "name": "BOA TARDE",
    "category": "Interações"
  },
  {
    "image": "/figuras/Interações/BOM DIA.png",
    "text": "BOM DIA",
    "name": "BOM DIA",
    "category": "Interações"
  },
  {
    "image": "/figuras/Interações/COM LICENÇA.png",
    "text": "COM LICENÇA",
    "name": "COM LICENÇA",
    "category": "Interações"
  },
  {
    "image": "/figuras/Interações/DESCULPA.png",
    "text": "DESCULPA",
    "name": "DESCULPA",
    "category": "Interações"
  },
  {
    "image": "/figuras/Interações/OBRIGADO.png",
    "text": "OBRIGADO",
    "name": "OBRIGADO",
    "category": "Interações"
  },
  {
    "image": "/figuras/Interações/OI.png",
    "text": "OI",
    "name": "OI",
    "category": "Interações"
  },
  {
    "image": "/figuras/Interações/POR FAVOR.png",
    "text": "POR FAVOR",
    "name": "POR FAVOR",
    "category": "Interações"
  },
  {
    "image": "/figuras/Interações/POR NADA.png",
    "text": "POR NADA",
    "name": "POR NADA",
    "category": "Interações"
  },
  {
    "image": "/figuras/Interações/TCHAU.png",
    "text": "TCHAU",
    "name": "TCHAU",
    "category": "Interações"
  },
  {
    "image": "/figuras/Natureza/AQUÁRIO.png",
    "text": "AQUÁRIO",
    "name": "AQUÁRIO",
    "category": "Natureza"
  },
  {
    "image": "/figuras/Natureza/CAHOEIRA.png",
    "text": "CAHOEIRA",
    "name": "CAHOEIRA",
    "category": "Natureza"
  },
  {
    "image": "/figuras/Natureza/CHUVA.png",
    "text": "CHUVA",
    "name": "CHUVA",
    "category": "Natureza"
  },
  {
    "image": "/figuras/Natureza/FLORESTA.png",
    "text": "FLORESTA",
    "name": "FLORESTA",
    "category": "Natureza"
  },
  {
    "image": "/figuras/Natureza/ILHA.png",
    "text": "ILHA",
    "name": "ILHA",
    "category": "Natureza"
  },
  {
    "image": "/figuras/Natureza/INVERNO.png",
    "text": "INVERNO",
    "name": "INVERNO",
    "category": "Natureza"
  },
  {
    "image": "/figuras/Natureza/MAR.png",
    "text": "MAR",
    "name": "MAR",
    "category": "Natureza"
  },
  {
    "image": "/figuras/Natureza/MONTANHA.png",
    "text": "MONTANHA",
    "name": "MONTANHA",
    "category": "Natureza"
  },
  {
    "image": "/figuras/Natureza/NEVE.png",
    "text": "NEVE",
    "name": "NEVE",
    "category": "Natureza"
  },
  {
    "image": "/figuras/Natureza/OUTONO.png",
    "text": "OUTONO",
    "name": "OUTONO",
    "category": "Natureza"
  },
  {
    "image": "/figuras/Natureza/PARQUE.png",
    "text": "PARQUE",
    "name": "PARQUE",
    "category": "Natureza"
  },
  {
    "image": "/figuras/Natureza/PRAIA.png",
    "text": "PRAIA",
    "name": "PRAIA",
    "category": "Natureza"
  },
  {
    "image": "/figuras/Natureza/PRIMAVERA.png",
    "text": "PRIMAVERA",
    "name": "PRIMAVERA",
    "category": "Natureza"
  },
  {
    "image": "/figuras/Natureza/RIO.png",
    "text": "RIO",
    "name": "RIO",
    "category": "Natureza"
  },
  {
    "image": "/figuras/Natureza/VENTO.png",
    "text": "VENTO",
    "name": "VENTO",
    "category": "Natureza"
  },
  {
    "image": "/figuras/Natureza/VERÃO.png",
    "text": "VERÃO",
    "name": "VERÃO",
    "category": "Natureza"
  },
  {
    "image": "/figuras/Natureza/ZOOLÓGICO.png",
    "text": "ZOOLÓGICO",
    "name": "ZOOLÓGICO",
    "category": "Natureza"
  },
  {
    "image": "/figuras/Natureza/ÁRVORE.png",
    "text": "ÁRVORE",
    "name": "ÁRVORE",
    "category": "Natureza"
  },
  {
    "image": "/figuras/Higiene/BANHO.png",
    "text": "BANHO",
    "name": "BANHO",
    "category": "Higiene"
  },
  {
    "image": "/figuras/Higiene/COCÔ.png",
    "text": "COCÔ",
    "name": "COCÔ",
    "category": "Higiene"
  },
  {
    "image": "/figuras/Higiene/COMER.png",
    "text": "COMER",
    "name": "COMER",
    "category": "Higiene"
  },
  {
    "image": "/figuras/Higiene/DORMIR.png",
    "text": "DORMIR",
    "name": "DORMIR",
    "category": "Higiene"
  },
  {
    "image": "/figuras/Higiene/ESCOVAR.png",
    "text": "ESCOVAR",
    "name": "ESCOVAR",
    "category": "Higiene"
  },
  {
    "image": "/figuras/Higiene/LAVAR.png",
    "text": "LAVAR",
    "name": "LAVAR",
    "category": "Higiene"
  },
  {
    "image": "/figuras/Higiene/PENTEAR.png",
    "text": "PENTEAR",
    "name": "PENTEAR",
    "category": "Higiene"
  },
  {
    "image": "/figuras/Higiene/XIXI.png",
    "text": "XIXI",
    "name": "XIXI",
    "category": "Higiene"
  },
  {
    "image": "/figuras/Números/CINCO.png",
    "text": "CINCO",
    "name": "CINCO",
    "category": "Números"
  },
  {
    "image": "/figuras/Números/DOIS.png",
    "text": "DOIS",
    "name": "DOIS",
    "category": "Números"
  },
  {
    "image": "/figuras/Números/NOVE.png",
    "text": "NOVE",
    "name": "NOVE",
    "category": "Números"
  },
  {
    "image": "/figuras/Números/OITO.png",
    "text": "OITO",
    "name": "OITO",
    "category": "Números"
  },
  {
    "image": "/figuras/Números/QUATRO.png",
    "text": "QUATRO",
    "name": "QUATRO",
    "category": "Números"
  },
  {
    "image": "/figuras/Números/SEIS.png",
    "text": "SEIS",
    "name": "SEIS",
    "category": "Números"
  },
  {
    "image": "/figuras/Números/SETE.png",
    "text": "SETE",
    "name": "SETE",
    "category": "Números"
  },
  {
    "image": "/figuras/Números/TRÊS.png",
    "text": "TRÊS",
    "name": "TRÊS",
    "category": "Números"
  },
  {
    "image": "/figuras/Números/UM.png",
    "text": "UM",
    "name": "UM",
    "category": "Números"
  },
  {
    "image": "/figuras/Números/ZERO.png",
    "text": "ZERO",
    "name": "ZERO",
    "category": "Números"
  },
  {
    "image": "/figuras/Perguntas/COMO.png",
    "text": "COMO",
    "name": "COMO",
    "category": "Perguntas"
  },
  {
    "image": "/figuras/Perguntas/ONDE.png",
    "text": "ONDE",
    "name": "ONDE",
    "category": "Perguntas"
  },
  {
    "image": "/figuras/Perguntas/PORQUE.png",
    "text": "PORQUE",
    "name": "PORQUE",
    "category": "Perguntas"
  },
  {
    "image": "/figuras/Perguntas/QUAL.png",
    "text": "QUAL",
    "name": "QUAL",
    "category": "Perguntas"
  },
  {
    "image": "/figuras/Perguntas/QUANDO.png",
    "text": "QUANDO",
    "name": "QUANDO",
    "category": "Perguntas"
  },
  {
    "image": "/figuras/Perguntas/QUEM.png",
    "text": "QUEM",
    "name": "QUEM",
    "category": "Perguntas"
  },
  {
    "image": "/figuras/Qualidades/BOM.png",
    "text": "BOM",
    "name": "BOM",
    "category": "Qualidades"
  },
  {
    "image": "/figuras/Qualidades/DIFÍCIL.png",
    "text": "DIFÍCIL",
    "name": "DIFÍCIL",
    "category": "Qualidades"
  },
  {
    "image": "/figuras/Qualidades/FRIO.png",
    "text": "FRIO",
    "name": "FRIO",
    "category": "Qualidades"
  },
  {
    "image": "/figuras/Qualidades/FÁCIL.png",
    "text": "FÁCIL",
    "name": "FÁCIL",
    "category": "Qualidades"
  },
  {
    "image": "/figuras/Qualidades/GRANDE.png",
    "text": "GRANDE",
    "name": "GRANDE",
    "category": "Qualidades"
  },
  {
    "image": "/figuras/Qualidades/LONGE.png",
    "text": "LONGE",
    "name": "LONGE",
    "category": "Qualidades"
  },
  {
    "image": "/figuras/Qualidades/MUITO.png",
    "text": "MUITO",
    "name": "MUITO",
    "category": "Qualidades"
  },
  {
    "image": "/figuras/Qualidades/PEQUENO.png",
    "text": "PEQUENO",
    "name": "PEQUENO",
    "category": "Qualidades"
  },
  {
    "image": "/figuras/Qualidades/PERTO.png",
    "text": "PERTO",
    "name": "PERTO",
    "category": "Qualidades"
  },
  {
    "image": "/figuras/Qualidades/POUCO.png",
    "text": "POUCO",
    "name": "POUCO",
    "category": "Qualidades"
  },
  {
    "image": "/figuras/Qualidades/QUENTE.png",
    "text": "QUENTE",
    "name": "QUENTE",
    "category": "Qualidades"
  },
  {
    "image": "/figuras/Qualidades/RUIM.png",
    "text": "RUIM",
    "name": "RUIM",
    "category": "Qualidades"
  },
  {
    "image": "/figuras/Vestuário/BERMUDA.png",
    "text": "BERMUDA",
    "name": "BERMUDA",
    "category": "Vestuário"
  },
  {
    "image": "/figuras/Vestuário/BLUSA DE FRIO.png",
    "text": "BLUSA DE FRIO",
    "name": "BLUSA DE FRIO",
    "category": "Vestuário"
  },
  {
    "image": "/figuras/Vestuário/BLUSA.png",
    "text": "BLUSA",
    "name": "BLUSA",
    "category": "Vestuário"
  },
  {
    "image": "/figuras/Vestuário/BONÉ.png",
    "text": "BONÉ",
    "name": "BONÉ",
    "category": "Vestuário"
  },
  {
    "image": "/figuras/Vestuário/CALCINHA.png",
    "text": "CALCINHA",
    "name": "CALCINHA",
    "category": "Vestuário"
  },
  {
    "image": "/figuras/Vestuário/CALÇA.png",
    "text": "CALÇA",
    "name": "CALÇA",
    "category": "Vestuário"
  },
  {
    "image": "/figuras/Vestuário/CAMISETA.png",
    "text": "CAMISETA",
    "name": "CAMISETA",
    "category": "Vestuário"
  },
  {
    "image": "/figuras/Vestuário/CASACO.png",
    "text": "CASACO",
    "name": "CASACO",
    "category": "Vestuário"
  },
  {
    "image": "/figuras/Vestuário/CHINELO.png",
    "text": "CHINELO",
    "name": "CHINELO",
    "category": "Vestuário"
  },
  {
    "image": "/figuras/Vestuário/CUECA.png",
    "text": "CUECA",
    "name": "CUECA",
    "category": "Vestuário"
  },
  {
    "image": "/figuras/Vestuário/GRAVATA.png",
    "text": "GRAVATA",
    "name": "GRAVATA",
    "category": "Vestuário"
  },
  {
    "image": "/figuras/Vestuário/LUVAS.png",
    "text": "LUVAS",
    "name": "LUVAS",
    "category": "Vestuário"
  },
  {
    "image": "/figuras/Vestuário/MEIA.png",
    "text": "MEIA",
    "name": "MEIA",
    "category": "Vestuário"
  },
  {
    "image": "/figuras/Vestuário/PANTUFAS.png",
    "text": "PANTUFAS",
    "name": "PANTUFAS",
    "category": "Vestuário"
  },
  {
    "image": "/figuras/Vestuário/RELÓGIO.png",
    "text": "RELÓGIO",
    "name": "RELÓGIO",
    "category": "Vestuário"
  },
  {
    "image": "/figuras/Vestuário/SAIA.png",
    "text": "SAIA",
    "name": "SAIA",
    "category": "Vestuário"
  },
  {
    "image": "/figuras/Vestuário/SALTO.png",
    "text": "SALTO",
    "name": "SALTO",
    "category": "Vestuário"
  },
  {
    "image": "/figuras/Vestuário/SAPATILHA.png",
    "text": "SAPATILHA",
    "name": "SAPATILHA",
    "category": "Vestuário"
  },
  {
    "image": "/figuras/Vestuário/TENIS.png",
    "text": "TENIS",
    "name": "TENIS",
    "category": "Vestuário"
  },
  {
    "image": "/figuras/Vestuário/TOUCA.png",
    "text": "TOUCA",
    "name": "TOUCA",
    "category": "Vestuário"
  },
  {
    "image": "/figuras/Vestuário/VESTIDO.png",
    "text": "VESTIDO",
    "name": "VESTIDO",
    "category": "Vestuário"
  },
  {
    "image": "/figuras/Vestuário/ÓCULOS.png",
    "text": "ÓCULOS",
    "name": "ÓCULOS",
    "category": "Vestuário"
  },
  {
    "image": "/figuras/Emoções/BRAVO.png",
    "text": "BRAVO",
    "name": "BRAVO",
    "category": "Emoções"
  },
  {
    "image": "/figuras/Emoções/CANSADO.png",
    "text": "CANSADO",
    "name": "CANSADO",
    "category": "Emoções"
  },
  {
    "image": "/figuras/Emoções/FELIZ.png",
    "text": "FELIZ",
    "name": "FELIZ",
    "category": "Emoções"
  },
  {
    "image": "/figuras/Emoções/MEDO.png",
    "text": "MEDO",
    "name": "MEDO",
    "category": "Emoções"
  },
  {
    "image": "/figuras/Emoções/SONO.png",
    "text": "SONO",
    "name": "SONO",
    "category": "Emoções"
  },
  {
    "image": "/figuras/Emoções/TRISTE.png",
    "text": "TRISTE",
    "name": "TRISTE",
    "category": "Emoções"
  },
  {
    "image": "/figuras/Tempo/AMANHÃ.png",
    "text": "AMANHÃ",
    "name": "AMANHÃ",
    "category": "Tempo"
  },
  {
    "image": "/figuras/Tempo/ANIVERSÁRIO.png",
    "text": "ANIVERSÁRIO",
    "name": "ANIVERSÁRIO",
    "category": "Tempo"
  },
  {
    "image": "/figuras/Tempo/ANO NOVO.png",
    "text": "ANO NOVO",
    "name": "ANO NOVO",
    "category": "Tempo"
  },
  {
    "image": "/figuras/Tempo/CARNAVAL.png",
    "text": "CARNAVAL",
    "name": "CARNAVAL",
    "category": "Tempo"
  },
  {
    "image": "/figuras/Tempo/CASAMENTO.png",
    "text": "CASAMENTO",
    "name": "CASAMENTO",
    "category": "Tempo"
  },
  {
    "image": "/figuras/Tempo/DIA.png",
    "text": "DIA",
    "name": "DIA",
    "category": "Tempo"
  },
  {
    "image": "/figuras/Tempo/FESTA JUNINA.png",
    "text": "FESTA JUNINA",
    "name": "FESTA JUNINA",
    "category": "Tempo"
  },
  {
    "image": "/figuras/Tempo/HOJE.png",
    "text": "HOJE",
    "name": "HOJE",
    "category": "Tempo"
  },
  {
    "image": "/figuras/Tempo/MÊS.png",
    "text": "MÊS",
    "name": "MÊS",
    "category": "Tempo"
  },
  {
    "image": "/figuras/Tempo/NATAL.png",
    "text": "NATAL",
    "name": "NATAL",
    "category": "Tempo"
  },
  {
    "image": "/figuras/Tempo/NOITE.png",
    "text": "NOITE",
    "name": "NOITE",
    "category": "Tempo"
  },
  {
    "image": "/figuras/Tempo/ONTEM.png",
    "text": "ONTEM",
    "name": "ONTEM",
    "category": "Tempo"
  },
  {
    "image": "/figuras/Tempo/PÁSCOA.png",
    "text": "PÁSCOA",
    "name": "PÁSCOA",
    "category": "Tempo"
  },
  {
    "image": "/figuras/Tempo/SEMANA.png",
    "text": "SEMANA",
    "name": "SEMANA",
    "category": "Tempo"
  }
]